    <ResidenceInterior>
      <LocalID>147201</LocalID>
      <InternalInteriorCoordinates>
        <X>-22.61353</X>
        <Y>-590.1432</Y>
        <Z>78.43091</Z>
      </InternalInteriorCoordinates>
      <Name>4 Intergrity Way Apt 28</Name>
      <IsTeleportEntry>true</IsTeleportEntry>
      <DisabledInteriorCoords>
        <X>0</X>
        <Y>0</Y>
        <Z>0</Z>
      </DisabledInteriorCoords>
      <Doors />
      <RequestIPLs />
      <RemoveIPLs />
      <InteriorSets />
      <InteriorEgressPosition>
        <X>-23.78597</X>
        <Y>-597.8651</Y>
        <Z>80.03111</Z>
      </InteriorEgressPosition>
      <InteriorEgressHeading>246.097</InteriorEgressHeading>
      <NeedsActivation>false</NeedsActivation>
      <NeedsSetDisabled>false</NeedsSetDisabled>
      <IsRestricted>false</IsRestricted>
      <IsWeaponRestricted>false</IsWeaponRestricted>
      <InteractPoints>
        <InteriorInteract xsi:type="ExitInteriorInteract">
          <Name>IntWayApt28Exit1</Name>
          <Position>
            <X>-23.78597</X>
            <Y>-597.8651</Y>
            <Z>80.03111</Z>
          </Position>
          <Heading>30.90518</Heading>
          <InteractDistance>1</InteractDistance>
          <CameraPosition>
            <X>0</X>
            <Y>0</Y>
            <Z>0</Z>
          </CameraPosition>
          <CameraDirection>
            <X>0</X>
            <Y>0</Y>
            <Z>0</Z>
          </CameraDirection>
          <CameraRotation>
            <Pitch>0</Pitch>
            <Roll>0</Roll>
            <Yaw>0</Yaw>
          </CameraRotation>
          <ButtonPromptText>Exit</ButtonPromptText>
          <AutoCamera>true</AutoCamera>
          <UseNavmesh>true</UseNavmesh>
          <WithWarp>false</WithWarp>
        </InteriorInteract>
        <InteriorInteract xsi:type="StandardInteriorInteract">
          <Name>IntWayApt28Std1</Name>
          <Position>
            <X>-22.03025</X>
            <Y>-585.5857</Y>
            <Z>79.23075</Z>
          </Position>
          <Heading>30.90518</Heading>
          <InteractDistance>1</InteractDistance>
          <CameraPosition>
            <X>-20.13322</X>
            <Y>-586.7794</Y>
            <Z>79.96764</Z>
          </CameraPosition>
          <CameraDirection>
            <X>-0.8326086</X>
            <Y>0.4589401</Y>
            <Z>-0.3100595</Z>
          </CameraDirection>
          <CameraRotation>
            <Pitch>-18.06281</Pitch>
            <Roll>-3.592124E-06</Roll>
            <Yaw>61.13612</Yaw>
          </CameraRotation>
          <ButtonPromptText>Interact</ButtonPromptText>
          <AutoCamera>true</AutoCamera>
          <UseNavmesh>true</UseNavmesh>
          <WithWarp>false</WithWarp>
        </InteriorInteract>
        <InteriorInteract xsi:type="ToiletInteract">
          <Name>IntWayApt28Toilet1</Name>
          <Position>
            <X>-43.14818</X>
            <Y>-583.9168</Y>
            <Z>78.83031</Z>
          </Position>
          <Heading>156.5145</Heading>
          <InteractDistance>1</InteractDistance>
          <CameraPosition>
            <X>-41.25925</X>
            <Y>-583.7449</Y>
            <Z>79.72494</Z>
          </CameraPosition>
          <CameraDirection>
            <X>-0.8764492</X>
            <Y>-0.2165945</Y>
            <Z>-0.4300276</Z>
          </CameraDirection>
          <CameraRotation>
            <Pitch>-25.46931</Pitch>
            <Roll>-6.619751E-06</Roll>
            <Yaw>103.8812</Yaw>
          </CameraRotation>
          <ButtonPromptText>Use Toilet</ButtonPromptText>
          <AutoCamera>true</AutoCamera>
          <UseNavmesh>false</UseNavmesh>
          <WithWarp>false</WithWarp>
          <IsStanding>false</IsStanding>
        </InteriorInteract>
        <InteriorInteract xsi:type="SinkInteract">
          <Name>IntWayApt28Sink1</Name>
          <Position>
            <X>-40.81684</X>
            <Y>-584.7047</Y>
            <Z>78.8303</Z>
          </Position>
          <Heading>160.8843</Heading>
          <InteractDistance>1</InteractDistance>
          <CameraPosition>
            <X>-39.37873</X>
            <Y>-584.9852</Y>
            <Z>79.57347</Z>
          </CameraPosition>
          <CameraDirection>
            <X>-0.9313787</X>
            <Y>-0.121525</Y>
            <Z>-0.3431697</Z>
          </CameraDirection>
          <CameraRotation>
            <Pitch>-20.07011</Pitch>
            <Roll>4.544862E-06</Roll>
            <Yaw>97.43388</Yaw>
          </CameraRotation>
          <ButtonPromptText>Use Sink</ButtonPromptText>
          <AutoCamera>true</AutoCamera>
          <UseNavmesh>false</UseNavmesh>
          <WithWarp>false</WithWarp>
          <IsScenario>false</IsScenario>
        </InteriorInteract>
        <InteriorInteract xsi:type="SinkInteract">
          <Name>IntWayApt28Sink2</Name>
          <Position>
            <X>-42.15263</X>
            <Y>-584.1649</Y>
            <Z>78.83798</Z>
          </Position>
          <Heading>159.9368</Heading>
          <InteractDistance>1</InteractDistance>
          <CameraPosition>
            <X>-39.37873</X>
            <Y>-584.9852</Y>
            <Z>79.57347</Z>
          </CameraPosition>
          <CameraDirection>
            <X>-0.9313787</X>
            <Y>-0.121525</Y>
            <Z>-0.3431697</Z>
          </CameraDirection>
          <CameraRotation>
            <Pitch>-20.07011</Pitch>
            <Roll>4.544862E-06</Roll>
            <Yaw>97.43388</Yaw>
          </CameraRotation>
          <ButtonPromptText>Use Sink</ButtonPromptText>
          <AutoCamera>true</AutoCamera>
          <UseNavmesh>false</UseNavmesh>
          <WithWarp>false</WithWarp>
          <IsScenario>false</IsScenario>
        </InteriorInteract>
      </InteractPoints>
      <ClearPositions>
        <Vector3>
          <X>-43.14818</X>
          <Y>-583.9168</Y>
          <Z>78.83031</Z>
        </Vector3>
      </ClearPositions>
      <RestInteracts>
        <RestInteract>
          <Name>IntWayApt28Rest1</Name>
          <Position>
            <X>-37.16466</X>
            <Y>-583.97</Y>
            <Z>78.8303</Z>
          </Position>
          <Heading>339.9454</Heading>
          <InteractDistance>1</InteractDistance>
          <CameraPosition>
            <X>-33.99035</X>
            <Y>-585.1405</Y>
            <Z>79.79942</Z>
          </CameraPosition>
          <CameraDirection>
            <X>-0.5844311</X>
            <Y>0.7171674</Y>
            <Z>-0.3796198</Z>
          </CameraDirection>
          <CameraRotation>
            <Pitch>-22.31013</Pitch>
            <Roll>9.228564E-06</Roll>
            <Yaw>39.17713</Yaw>
          </CameraRotation>
          <ButtonPromptText>Sleep</ButtonPromptText>
          <AutoCamera>true</AutoCamera>
          <UseNavmesh>true</UseNavmesh>
          <WithWarp>false</WithWarp>
          <StartAnimations />
          <LoopAnimations />
          <EndAnimations />
          <UseDefaultAnimations>true</UseDefaultAnimations>
        </RestInteract>
      </RestInteracts>
      <OutfitInteracts>
        <OutfitInteract>
          <Name>IntWayApt28Outfit1</Name>
          <Position>
            <X>-38.30136</X>
            <Y>-589.6819</Y>
            <Z>78.83025</Z>
          </Position>
          <Heading>332.1915</Heading>
          <InteractDistance>1</InteractDistance>
          <CameraPosition>
            <X>-37.52896</X>
            <Y>-587.5145</Y>
            <Z>79.43327</Z>
          </CameraPosition>
          <CameraDirection>
            <X>-0.3625692</X>
            <Y>-0.8973691</Y>
            <Z>-0.2515399</Z>
          </CameraDirection>
          <CameraRotation>
            <Pitch>-14.56865</Pitch>
            <Roll>2.205343E-06</Roll>
            <Yaw>157.9995</Yaw>
          </CameraRotation>
          <ButtonPromptText>Change Outfit</ButtonPromptText>
          <AutoCamera>true</AutoCamera>
          <UseNavmesh>true</UseNavmesh>
          <WithWarp>false</WithWarp>
        </OutfitInteract>
      </OutfitInteracts>
      <InventoryInteracts>
        <InventoryInteract>
          <Name>IntWayApt28Inventory1</Name>
          <Position>
            <X>-13.06198</X>
            <Y>-589.3143</Y>
            <Z>79.43072</Z>
          </Position>
          <Heading>167.0125</Heading>
          <InteractDistance>1</InteractDistance>
          <CameraPosition>
            <X>-16.69204</X>
            <Y>-587.3567</Y>
            <Z>80.19315</Z>
          </CameraPosition>
          <CameraDirection>
            <X>0.7653685</X>
            <Y>-0.546774</Y>
            <Z>-0.3394839</Z>
          </CameraDirection>
          <CameraRotation>
            <Pitch>-19.84543</Pitch>
            <Roll>1.633822E-05</Roll>
            <Yaw>-125.5418</Yaw>
          </CameraRotation>
          <ButtonPromptText>Open Fridge</ButtonPromptText>
          <AutoCamera>true</AutoCamera>
          <UseNavmesh>false</UseNavmesh>
          <WithWarp>false</WithWarp>
          <CanAccessItems>true</CanAccessItems>
          <CanAccessWeapons>false</CanAccessWeapons>
          <CanAccessCash>false</CanAccessCash>
          <AllowedItemTypes>
            <ItemType>None</ItemType>
          </AllowedItemTypes>
          <DisallowedItemTypes />
          <RemoveMenuBanner>true</RemoveMenuBanner>
          <Title>Fridge</Title>
          <Description>Access Drinks</Description>
        </InventoryInteract>
        <InventoryInteract>
          <Name>IntWayApt28Inventory2</Name>
          <Position>
            <X>-14.93999</X>
            <Y>-588.6166</Y>
            <Z>79.43072</Z>
          </Position>
          <Heading>163.9242</Heading>
          <InteractDistance>1</InteractDistance>
          <CameraPosition>
            <X>-16.69204</X>
            <Y>-587.3567</Y>
            <Z>80.19315</Z>
          </CameraPosition>
          <CameraDirection>
            <X>0.7653685</X>
            <Y>-0.546774</Y>
            <Z>-0.3394839</Z>
          </CameraDirection>
          <CameraRotation>
            <Pitch>-19.84543</Pitch>
            <Roll>1.633822E-05</Roll>
            <Yaw>-125.5418</Yaw>
          </CameraRotation>
          <ButtonPromptText>Open Pantry</ButtonPromptText>
          <AutoCamera>true</AutoCamera>
          <UseNavmesh>false</UseNavmesh>
          <WithWarp>false</WithWarp>
          <CanAccessItems>true</CanAccessItems>
          <CanAccessWeapons>false</CanAccessWeapons>
          <CanAccessCash>false</CanAccessCash>
          <AllowedItemTypes>
            <ItemType>None</ItemType>
            <ItemType>None</ItemType>
          </AllowedItemTypes>
          <DisallowedItemTypes />
          <RemoveMenuBanner>true</RemoveMenuBanner>
          <Title>Pantry</Title>
          <Description>Access Food</Description>
        </InventoryInteract>
        <InventoryInteract>
          <Name>IntWayApt28Inventory3</Name>
          <Position>
            <X>-11.94945</X>
            <Y>-585.4624</Y>
            <Z>79.43072</Z>
          </Position>
          <Heading>66.99971</Heading>
          <InteractDistance>1</InteractDistance>
          <CameraPosition>
            <X>-10.47478</X>
            <Y>-583.9545</Y>
            <Z>80.17472</Z>
          </CameraPosition>
          <CameraDirection>
            <X>-0.7169776</X>
            <Y>-0.6106874</Y>
            <Z>-0.3361607</Z>
          </CameraDirection>
          <CameraRotation>
            <Pitch>-19.64314</Pitch>
            <Roll>-5.439177E-06</Roll>
            <Yaw>130.4228</Yaw>
          </CameraRotation>
          <ButtonPromptText>Access Items</ButtonPromptText>
          <AutoCamera>true</AutoCamera>
          <UseNavmesh>false</UseNavmesh>
          <WithWarp>false</WithWarp>
          <CanAccessItems>true</CanAccessItems>
          <CanAccessWeapons>false</CanAccessWeapons>
          <CanAccessCash>false</CanAccessCash>
          <AllowedItemTypes />
          <DisallowedItemTypes>
            <ItemType>None</ItemType>
            <ItemType>None</ItemType>
            <ItemType>None</ItemType>
          </DisallowedItemTypes>
          <RemoveMenuBanner>true</RemoveMenuBanner>
          <Title />
          <Description />
        </InventoryInteract>
        <InventoryInteract>
          <Name>IntWayApt28Inventory4</Name>
          <Position>
            <X>-32.57137</X>
            <Y>-584.2276</Y>
            <Z>78.86552</Z>
          </Position>
          <Heading>249.758</Heading>
          <InteractDistance>1</InteractDistance>
          <CameraPosition>
            <X>-33.86394</X>
            <Y>-585.8267</Y>
            <Z>79.60912</Z>
          </CameraPosition>
          <CameraDirection>
            <X>0.6186898</X>
            <Y>0.703401</Y>
            <Z>-0.3499286</Z>
          </CameraDirection>
          <CameraRotation>
            <Pitch>-20.48295</Pitch>
            <Roll>1.549372E-05</Roll>
            <Yaw>-41.33386</Yaw>
          </CameraRotation>
          <ButtonPromptText>Cash Drawer</ButtonPromptText>
          <AutoCamera>true</AutoCamera>
          <UseNavmesh>false</UseNavmesh>
          <WithWarp>false</WithWarp>
          <CanAccessItems>false</CanAccessItems>
          <CanAccessWeapons>false</CanAccessWeapons>
          <CanAccessCash>true</CanAccessCash>
          <AllowedItemTypes />
          <DisallowedItemTypes />
          <RemoveMenuBanner>true</RemoveMenuBanner>
          <Title />
          <Description />
        </InventoryInteract>
        <InventoryInteract>
          <Name>IntWayApt28Inventory5</Name>
          <Position>
            <X>-11.75585</X>
            <Y>-598.9</Y>
            <Z>79.43021</Z>
          </Position>
          <Heading>159.8243</Heading>
          <InteractDistance>1</InteractDistance>
          <CameraPosition>
            <X>-9.712107</X>
            <Y>-598.9153</Y>
            <Z>80.15553</Z>
          </CameraPosition>
          <CameraDirection>
            <X>-0.9368092</X>
            <Y>-0.1051063</Y>
            <Z>-0.3336782</Z>
          </CameraDirection>
          <CameraRotation>
            <Pitch>-19.49218</Pitch>
            <Roll>-4.528405E-07</Roll>
            <Yaw>96.40159</Yaw>
          </CameraRotation>
          <ButtonPromptText>Weapons Locker</ButtonPromptText>
          <AutoCamera>true</AutoCamera>
          <UseNavmesh>false</UseNavmesh>
          <WithWarp>false</WithWarp>
          <CanAccessItems>false</CanAccessItems>
          <CanAccessWeapons>true</CanAccessWeapons>
          <CanAccessCash>false</CanAccessCash>
          <AllowedItemTypes />
          <DisallowedItemTypes />
          <RemoveMenuBanner>true</RemoveMenuBanner>
          <Title />
          <Description />
        </InventoryInteract>
      </InventoryInteracts>
    </ResidenceInterior>